{
  "app": {
    "[project]/app/_not-found/page": [
      "static/media/dc6d2a64e9dbf3bc-s.p.11~i--ovv74c_.woff2",
      "static/media/797e433ab948586e-s.p.0.q-h669a_dqa.woff2",
      "static/media/69d6ef502243698c-s.p.0png7hpupgyks.woff2"
    ],
    "[project]/app/dashboard/page": [
      "static/media/dc6d2a64e9dbf3bc-s.p.11~i--ovv74c_.woff2",
      "static/media/797e433ab948586e-s.p.0.q-h669a_dqa.woff2",
      "static/media/69d6ef502243698c-s.p.0png7hpupgyks.woff2"
    ],
    "[project]/app/login/page": [
      "static/media/dc6d2a64e9dbf3bc-s.p.11~i--ovv74c_.woff2",
      "static/media/797e433ab948586e-s.p.0.q-h669a_dqa.woff2",
      "static/media/69d6ef502243698c-s.p.0png7hpupgyks.woff2"
    ],
    "[project]/app/page": [
      "static/media/dc6d2a64e9dbf3bc-s.p.11~i--ovv74c_.woff2",
      "static/media/797e433ab948586e-s.p.0.q-h669a_dqa.woff2",
      "static/media/69d6ef502243698c-s.p.0png7hpupgyks.woff2"
    ],
    "[project]/app/pantry/page": [
      "static/media/dc6d2a64e9dbf3bc-s.p.11~i--ovv74c_.woff2",
      "static/media/797e433ab948586e-s.p.0.q-h669a_dqa.woff2",
      "static/media/69d6ef502243698c-s.p.0png7hpupgyks.woff2"
    ],
    "[project]/app/recipes/[id]/page": [
      "static/media/dc6d2a64e9dbf3bc-s.p.11~i--ovv74c_.woff2",
      "static/media/797e433ab948586e-s.p.0.q-h669a_dqa.woff2",
      "static/media/69d6ef502243698c-s.p.0png7hpupgyks.woff2"
    ]
  },
  "appUsingSizeAdjust": true,
  "pages": {},
  "pagesUsingSizeAdjust": false
}